releng-tool/__init__.py
releng-tool/__main__.py
releng_tool/__init__.py
releng_tool/__main__.py
releng_tool/defs.py
releng_tool/exceptions.py
releng_tool/opts.py
releng_tool/prerequisites.py
releng_tool/registry.py
releng_tool/stats.py
releng_tool/support.py
releng_tool/api/__init__.py
releng_tool/data/__init__.py
releng_tool/data/licenses/README
releng_tool/data/licenses/__init__.py
releng_tool/data/licenses/data.json
releng_tool/engine/__init__.py
releng_tool/engine/bootstrap.py
releng_tool/engine/build.py
releng_tool/engine/configure.py
releng_tool/engine/extract.py
releng_tool/engine/fetch.py
releng_tool/engine/fetch_post.py
releng_tool/engine/init.py
releng_tool/engine/install.py
releng_tool/engine/license.py
releng_tool/engine/patch.py
releng_tool/engine/post.py
releng_tool/engine/sbom.py
releng_tool/engine/script_env.py
releng_tool/engine/suggest.py
releng_tool/engine/vsdevcmd.py
releng_tool/engine/autotools/__init__.py
releng_tool/engine/autotools/build.py
releng_tool/engine/autotools/configure.py
releng_tool/engine/autotools/install.py
releng_tool/engine/cargo/__init__.py
releng_tool/engine/cargo/build.py
releng_tool/engine/cargo/install.py
releng_tool/engine/cmake/__init__.py
releng_tool/engine/cmake/build.py
releng_tool/engine/cmake/configure.py
releng_tool/engine/cmake/install.py
releng_tool/engine/make/__init__.py
releng_tool/engine/make/build.py
releng_tool/engine/make/configure.py
releng_tool/engine/make/install.py
releng_tool/engine/meson/__init__.py
releng_tool/engine/meson/build.py
releng_tool/engine/meson/configure.py
releng_tool/engine/meson/install.py
releng_tool/engine/python/__init__.py
releng_tool/engine/python/build.py
releng_tool/engine/python/install.py
releng_tool/engine/scons/__init__.py
releng_tool/engine/scons/build.py
releng_tool/engine/scons/configure.py
releng_tool/engine/scons/install.py
releng_tool/engine/script/__init__.py
releng_tool/engine/script/build.py
releng_tool/engine/script/configure.py
releng_tool-2.6.0.dist-info/licenses/LICENSE
releng_tool-2.6.0.dist-info/METADATA
releng_tool-2.6.0.dist-info/WHEEL
releng_tool-2.6.0.dist-info/entry_points.txt
releng_tool-2.6.0.dist-info/top_level.txt
releng_tool-2.6.0.dist-info/RECORD
