Metadata-Version: 2.4
Name: releng-tool
Version: 2.6.0
Summary: A tool to manage the building of packages
Author-email: releng-tool <releng@releng.io>
Project-URL: Homepage, https://releng.io
Project-URL: Documentation, https://docs.releng.io
Project-URL: Source, https://github.com/releng-tool/releng-tool
Classifier: Development Status :: 5 - Production/Stable
Classifier: Environment :: Console
Classifier: Operating System :: OS Independent
Classifier: Programming Language :: Python :: 3 :: Only
Classifier: Programming Language :: Python :: 3
Classifier: Programming Language :: Python :: 3.9
Classifier: Programming Language :: Python :: 3.10
Classifier: Programming Language :: Python :: 3.11
Classifier: Programming Language :: Python :: 3.12
Classifier: Programming Language :: Python :: 3.13
Classifier: Topic :: Software Development
Classifier: Topic :: Software Development :: Build Tools
Requires-Python: >=3.9
License-File: LICENSE
Requires-Dist: installer>=0.5.0
Provides-Extra: statistics
Requires-Dist: matplotlib; extra == "statistics"
Dynamic: license-file
